face_extractor/__init__.py
face_extractor/face_extractor.py
flare_face_extractor-0.0.6.dist-info/LICENSE
flare_face_extractor-0.0.6.dist-info/METADATA
flare_face_extractor-0.0.6.dist-info/WHEEL
flare_face_extractor-0.0.6.dist-info/top_level.txt
flare_face_extractor-0.0.6.dist-info/RECORD
