Metadata-Version: 2.1
Name: flare-face-extractor
Version: 0.0.6
Summary: A small example package
Home-page: https://github.com/Flare-FYDP/facial-extractor
Author: flare
Author-email: author@example.com
License: UNKNOWN
Project-URL: Bug Tracker, https://github.com/Flare-FYDP/facial-extractor/issues
Platform: UNKNOWN
Classifier: Programming Language :: Python :: 3
Classifier: License :: OSI Approved :: MIT License
Classifier: Operating System :: OS Independent
Requires-Python: >=3.6
License-File: LICENSE
Requires-Dist: numpy
Requires-Dist: opencv-python-headless
